[
  {
    "id": 1,
    "name": "冰霜之箭",
    "icon":"Skill_GongShou_6",
	"desc":"聚集冰元素之力的箭矢\n能减少敌人的移动速度,造成200%的伤害",
	"applyType":"SingleTarget",
	"applyProperty":"Attack",
	"applyValue":200,
	"applyTime":0,
	"mp":50,
	"coldTime":5,
	"applicableRole":"Archer",
	"needLevel":5,
	"maxLevel":10,
	"releaseType":"Enemy",
	"distance":5,
	"effectType":"Slow",
	"effectName":"e_bszj",
	"effectApplyValue":3,
	"skillPosType":"SkillPos1",
	"skillType":"Initiative",
	"upPoint":1,
	"animCondition":2,
	"animationTime":0.3,
	"skillDataConfiger":"SkillTemplate/BSZJTemplate"
  },
 
    
  {
    "id": 2,
    "name": "流光星陨",
    "icon":"Skill_GongShou_8",
	"desc":"向天空发出一只箭矢后将有火元素的箭雨降落\n大范围爆炸攻击,造成500%的伤害",
	"applyType":"MultiTarget",
	"applyProperty":"Attack",
	"applyValue":500,
	"applyTime":0,
	"mp":200,
	"coldTime":15,
	"applicableRole":"Archer",
	"needLevel":15,
	"maxLevel":10,
	"releaseType":"Position",
	"distance":8,
	"effectType":"Fly",
	"effectName":"e_lgxy",
	"effectApplyValue":2,
	"skillPosType":"SkillPos3",
	"skillType":"Initiative",
	"upPoint":1,
	"animCondition":4,
	"animationTime":0.3,
	"skillDataConfiger":"SkillTemplate/LGXYTemplate"
  }
   ,
  {
    "id": 3,
    "name": "雷神之怒",
    "icon":"Skill_GongShou_39",
	"desc":"发射出带有雷神之力的闪电箭\n范围攻击,有一定几率眩晕敌人3秒,造成400%的伤害",
	"applyType":"MultiTarget",
	"applyProperty":"Attack",
	"applyValue":400,
	"applyTime":0,
	"mp":100,
	"coldTime":10,
	"applicableRole":"Archer",
	"needLevel":10,
	"maxLevel":10,
	"releaseType":"Position",
	"distance":8,
	"effectType":"Dizzy",
	"effectName":"e_lszn",
	"effectApplyValue":50,
	"skillPosType":"SkillPos2",
	"skillType":"Initiative",
	"upPoint":1,
	"animCondition":3,
	"animationTime":0.3,
	"skillDataConfiger":"SkillTemplate/LSZNTemplate"
  }

]